kritrima_ai/__init__.py
kritrima_ai/__main__.py
kritrima_ai/app.py
kritrima_ai/cli.py
kritrima_ai/version.py
kritrima_ai/agent/__init__.py
kritrima_ai/agent/agent_loop.py
kritrima_ai/agent/base_tool.py
kritrima_ai/agent/tool_registry.py
kritrima_ai/config/__init__.py
kritrima_ai/config/app_config.py
kritrima_ai/config/providers.py
kritrima_ai/config/setup_wizard.py
kritrima_ai/providers/__init__.py
kritrima_ai/providers/ai_client.py
kritrima_ai/providers/model_manager.py
kritrima_ai/security/__init__.py
kritrima_ai/security/approval.py
kritrima_ai/security/encryption.py
kritrima_ai/security/monitor.py
kritrima_ai/security/sandbox.py
kritrima_ai/security/validator.py
kritrima_ai/storage/__init__.py
kritrima_ai/storage/command_history.py
kritrima_ai/storage/session_manager.py
kritrima_ai/tools/__init__.py
kritrima_ai/tools/code_analysis.py
kritrima_ai/tools/command_execution.py
kritrima_ai/tools/file_operations.py
kritrima_ai/tools/full_context.py
kritrima_ai/tools/patch_operations.py
kritrima_ai/tools/project_management.py
kritrima_ai/tools/system_info.py
kritrima_ai/tools/workflow_management.py
kritrima_ai/ui/__init__.py
kritrima_ai/ui/interactive_prompts.py
kritrima_ai/ui/rich_display.py
kritrima_ai/ui/terminal_interface.py
kritrima_ai/ui/widgets/__init__.py
kritrima_ai/ui/widgets/advanced_input.py
kritrima_ai/ui/widgets/chat_components.py
kritrima_ai/ui/widgets/overlays.py
kritrima_ai/ui/widgets/selection_components.py
kritrima_ai/ui/widgets/spinner.py
kritrima_ai/ui/widgets/status_components.py
kritrima_ai/ui/widgets/text_buffer.py
kritrima_ai/utils/__init__.py
kritrima_ai/utils/api_key_validator.py
kritrima_ai/utils/bug_reporter.py
kritrima_ai/utils/connection_tester.py
kritrima_ai/utils/file_utils.py
kritrima_ai/utils/format_command.py
kritrima_ai/utils/git_utils.py
kritrima_ai/utils/input_utils.py
kritrima_ai/utils/logger.py
kritrima_ai/utils/notifications.py
kritrima_ai/utils/package_manager.py
kritrima_ai/utils/response_utils.py
kritrima_ai_cli-1.1.0.dist-info/METADATA
kritrima_ai_cli-1.1.0.dist-info/WHEEL
kritrima_ai_cli-1.1.0.dist-info/entry_points.txt
kritrima_ai_cli-1.1.0.dist-info/top_level.txt
kritrima_ai_cli-1.1.0.dist-info/RECORD
