Metadata-Version: 2.4
Name: kritrima-ai-cli
Version: 1.1.0
Summary: Comprehensive AI-powered CLI assistant with autonomous agent capabilities
Home-page: https://github.com/kritrima/kritrima-ai-cli
Author: Kritrima AI Team
Author-email: Kritrima AI <contact@kritrima.ai>
License-Expression: MIT
Project-URL: Homepage, https://github.com/kritrima/kritrima-ai-cli
Project-URL: Documentation, https://docs.kritrima.ai
Project-URL: Repository, https://github.com/kritrima/kritrima-ai-cli
Project-URL: Bug Tracker, https://github.com/kritrima/kritrima-ai-cli/issues
Keywords: ai,cli,assistant,code-generation,automation,development-tools
Platform: any
Classifier: Development Status :: 5 - Production/Stable
Classifier: Intended Audience :: Developers
Classifier: Operating System :: OS Independent
Classifier: Programming Language :: Python :: 3
Classifier: Programming Language :: Python :: 3.8
Classifier: Programming Language :: Python :: 3.9
Classifier: Programming Language :: Python :: 3.10
Classifier: Programming Language :: Python :: 3.11
Classifier: Programming Language :: Python :: 3.12
Classifier: Programming Language :: Python :: 3.13
Classifier: Topic :: Software Development
Classifier: Topic :: Scientific/Engineering :: Artificial Intelligence
Classifier: Environment :: Console
Requires-Python: >=3.8
Requires-Dist: openai>=1.54.0
Requires-Dist: anthropic>=0.7.0
Requires-Dist: click>=8.1.0
Requires-Dist: rich>=13.7.0
Requires-Dist: textual>=0.45.0
Requires-Dist: pydantic>=2.5.0
Requires-Dist: httpx>=0.25.0
Requires-Dist: aiofiles>=23.2.0
Requires-Dist: gitpython>=3.1.40
Requires-Dist: psutil>=5.9.0
Requires-Dist: cryptography>=41.0.0
Requires-Dist: pillow>=10.1.0
Requires-Dist: python-dotenv>=1.0.0
Requires-Dist: typer>=0.9.0
Requires-Dist: pyyaml>=6.0.1
Requires-Dist: platformdirs>=4.0.0
Requires-Dist: watchdog>=3.0.0
Requires-Dist: inquirer>=3.1.0
Requires-Dist: colorama>=0.4.6
Requires-Dist: keyring>=24.3.0
Requires-Dist: prompt-toolkit>=3.0.41
Requires-Dist: asyncio-mqtt>=0.16.0
Requires-Dist: chardet>=5.2.0
Requires-Dist: toml>=0.10.2
Requires-Dist: nest-asyncio>=1.5.8
Requires-Dist: jinja2>=3.1.0
Requires-Dist: requests>=2.31.0
Requires-Dist: beautifulsoup4>=4.12.0
Requires-Dist: sqlalchemy>=2.0.0
Requires-Dist: pandas>=2.0.0
Requires-Dist: numpy>=1.24.0
Requires-Dist: scipy>=1.10.0
Requires-Dist: matplotlib>=3.7.0
Requires-Dist: plotly>=5.15.0
Requires-Dist: uvloop>=0.19.0; sys_platform != "win32"
Requires-Dist: winloop>=0.1.0; sys_platform == "win32"
Provides-Extra: dev
Requires-Dist: pytest>=7.4.0; extra == "dev"
Requires-Dist: pytest-asyncio>=0.21.0; extra == "dev"
Requires-Dist: pytest-cov>=4.1.0; extra == "dev"
Requires-Dist: black>=23.9.0; extra == "dev"
Requires-Dist: isort>=5.12.0; extra == "dev"
Requires-Dist: flake8>=6.1.0; extra == "dev"
Requires-Dist: mypy>=1.6.0; extra == "dev"
Requires-Dist: pre-commit>=3.4.0; extra == "dev"
Dynamic: author
Dynamic: home-page
Dynamic: platform
Dynamic: requires-python
